pytwis/__init__.py
pytwis/pytwis.py
pytwis/pytwis_clt.py
pytwis/pytwis_clt_constants.py
pytwis/pytwis_constants.py
pytwis-0.5.1.dist-info/METADATA
pytwis-0.5.1.dist-info/RECORD
pytwis-0.5.1.dist-info/WHEEL
pytwis-0.5.1.dist-info/entry_points.txt
pytwis-0.5.1.dist-info/top_level.txt
