Metadata-Version: 2.1
Name: pytwis
Version: 0.5.1
Summary: A twitter-toy-clone backend using Python and Redis
Home-page: https://renweizhukov.github.io/pytwis
Author: Wei Ren
Author-email: renwei2004@gmail.com
License: UNKNOWN
Project-URL: Bug Reports, https://github.com/renweizhukov/pytwis/issues
Project-URL: Documentation, https://renweizhukov.github.io/pytwis
Project-URL: Source, https://github.com/renweizhukov/pytwis
Keywords: redis twitter python3.6
Platform: UNKNOWN
Classifier: Development Status :: 4 - Beta
Classifier: Intended Audience :: Developers
Classifier: Topic :: Database :: Database Engines/Servers
Classifier: License :: OSI Approved :: Apache Software License
Classifier: Programming Language :: Python :: 3.6
Requires-Python: >=3.6
Provides-Extra: test
Requires-Dist: parse
Requires-Dist: redis
Requires-Dist: setuptools
Requires-Dist: Werkzeug
Provides-Extra: test
Requires-Dist: coverage; extra == 'test'
